adxtools/__init__.py
adxtools/__main__.py
adxtools/adx_conversion.py
adxtools/ahx_conversion.py
adxtools/aix_conversion.py
adxtools-0.1.1.dist-info/LICENSE
adxtools-0.1.1.dist-info/METADATA
adxtools-0.1.1.dist-info/WHEEL
adxtools-0.1.1.dist-info/top_level.txt
adxtools-0.1.1.dist-info/RECORD
